ymliu_tool/__init__.py
ymliu_tool/cli.py
ymliu_tool-0.1.0.dist-info/METADATA
ymliu_tool-0.1.0.dist-info/WHEEL
ymliu_tool-0.1.0.dist-info/entry_points.txt
ymliu_tool-0.1.0.dist-info/top_level.txt
ymliu_tool-0.1.0.dist-info/RECORD
