Metadata-Version: 2.4
Name: ymliu-tool
Version: 0.1.0
Summary: A simple utility tool by ymliu
Author-email: ymliu <ymliu@example.com>
License: MIT
Project-URL: Homepage, https://github.com/ymliu/ymliu-tool
Project-URL: Repository, https://github.com/ymliu/ymliu-tool
Project-URL: Issues, https://github.com/ymliu/ymliu-tool/issues
Keywords: utility,tool,cli
Classifier: Development Status :: 3 - Alpha
Classifier: Intended Audience :: Developers
Classifier: License :: OSI Approved :: MIT License
Classifier: Programming Language :: Python :: 3
Classifier: Programming Language :: Python :: 3.8
Classifier: Programming Language :: Python :: 3.9
Classifier: Programming Language :: Python :: 3.10
Classifier: Programming Language :: Python :: 3.11
Classifier: Programming Language :: Python :: 3.12
Classifier: Topic :: Utilities
Requires-Python: >=3.8
Requires-Dist: click>=8.0.0
Provides-Extra: dev
Requires-Dist: pytest>=7.0.0; extra == "dev"
Requires-Dist: black>=23.0.0; extra == "dev"
